README.md
setup.py
lbrlabs_pulumi_aws_tailscalebastion/__init__.py
lbrlabs_pulumi_aws_tailscalebastion/_utilities.py
lbrlabs_pulumi_aws_tailscalebastion/bastion.py
lbrlabs_pulumi_aws_tailscalebastion/provider.py
lbrlabs_pulumi_aws_tailscalebastion/pulumi-plugin.json
lbrlabs_pulumi_aws_tailscalebastion/py.typed
lbrlabs_pulumi_aws_tailscalebastion.egg-info/PKG-INFO
lbrlabs_pulumi_aws_tailscalebastion.egg-info/SOURCES.txt
lbrlabs_pulumi_aws_tailscalebastion.egg-info/dependency_links.txt
lbrlabs_pulumi_aws_tailscalebastion.egg-info/not-zip-safe
lbrlabs_pulumi_aws_tailscalebastion.egg-info/requires.txt
lbrlabs_pulumi_aws_tailscalebastion.egg-info/top_level.txt