Metadata-Version: 2.1
Name: lbrlabs-pulumi-aws-tailscalebastion
Version: 0.0.6a1666050329
Summary: A Pulumi package for creating a tailscale bastion in AWS.
Home-page: UNKNOWN
License: UNKNOWN
Project-URL: Repository, https://github.com/lbrlabs/pulumi-aws-tailscale
Platform: UNKNOWN
